[
    {
        "title": "Test Title",
        "text": "Test text"
    },
    {
        "title": "Test Title",
        "text": "Make breakfast",
        "note_id": "e489"
    },
    {
        "title": "Test Title",
        "text": "Make breakfast",
        "note_id": "c730"
    },
    {
        "title": "Test Title 7",
        "text": "Make breakfast 7",
        "note_id": "a43f"
    },
    {
        "title": "Test Title 8",
        "text": "7 Make breakfast 7",
        "note_id": "5132"
    },
    {
        "title": "Test Title 8",
        "text": "7 Make breakfast 7",
        "note_id": "90cd"
    },
    {
        "title": "Test Title 8",
        "text": "7 Make breakfast 7",
        "note_id": "35f8"
    }
]